{
  "project_info": {
    "project_number": "927094355107",
    "project_id": "tizichibidoll",
    "storage_bucket": "tizichibidoll.appspot.com"
  },
  "client": [
    {
      "client_info": {
        "mobilesdk_app_id": "1:927094355107:android:66f522454eafb6190e3b16",
        "android_client_info": {
          "package_name": "com.apollo.tizi.chibi.doll"
        }
      },
      "oauth_client": [],
      "api_key": [
        {
          "current_key": "AIzaSyDUlJai1pCqHWJED5Q8_Tuc_4TIrdqchxA"
        }
      ],
      "services": {
        "appinvite_service": {
          "other_platform_oauth_client": []
        }
      }
    }
  ],
  "configuration_version": "1"
}